didcomm_messaging-0.1.0.dist-info/METADATA
didcomm_messaging-0.1.0.dist-info/WHEEL
didcomm_messaging-0.1.0.dist-info/licenses/LICENSE
didcomm_messaging/__init__.py
didcomm_messaging/crypto/__init__.py
didcomm_messaging/crypto/backend/__init__.py
didcomm_messaging/crypto/backend/askar.py
didcomm_messaging/crypto/backend/authlib.py
didcomm_messaging/crypto/backend/basic.py
didcomm_messaging/crypto/base.py
didcomm_messaging/crypto/jwe.py
didcomm_messaging/multiformats/__init__.py
didcomm_messaging/multiformats/multibase.py
didcomm_messaging/multiformats/multicodec.py
didcomm_messaging/packaging.py
didcomm_messaging/quickstart.py
didcomm_messaging/resolver/__init__.py
didcomm_messaging/resolver/peer.py
didcomm_messaging/resolver/web.py
didcomm_messaging/routing.py
didcomm_messaging-0.1.0.dist-info/RECORD
