Metadata-Version: 2.1
Name: didcomm-messaging
Version: 0.1.0
Summary: DIDComm Messaging implemented with swappable backends.
Author-Email: Daniel Bluhm <dbluhm@pm.me>, Colton Wolkins <colton@indicio.tech>, Micah Peltier <micah@indicio.tech>
License: Apache-2.0
Requires-Python: >=3.9
Requires-Dist: base58>=2.1.1
Requires-Dist: pydid>=0.4.2
Requires-Dist: aries-askar>=0.2.9; extra == "askar"
Requires-Dist: did-peer-2>=0.1.2; extra == "did-peer"
Requires-Dist: did-peer-4>=0.1.2; extra == "did-peer"
Requires-Dist: authlib>=1.2.1; extra == "authlib"
Requires-Dist: pycryptodomex>=3.19.0; extra == "authlib"
Provides-Extra: askar
Provides-Extra: did_peer
Provides-Extra: authlib
